intake_coops/__init__.py
intake_coops/coops.py
intake_coops/coops_cat.py
intake_coops-0.4.3.dist-info/licenses/LICENSE.txt
intake_coops-0.4.3.dist-info/METADATA
intake_coops-0.4.3.dist-info/WHEEL
intake_coops-0.4.3.dist-info/entry_points.txt
intake_coops-0.4.3.dist-info/top_level.txt
intake_coops-0.4.3.dist-info/RECORD
