Metadata-Version: 2.4
Name: intake_coops
Version: 0.4.3
Summary: Intake interface to NOAA CO-OPS data
Home-page: https://github.com/axiom-data-science/intake-coops
Author: Axiom Data Science
Author-email: kthyng@axds.co
License: MIT
Classifier: Development Status :: 5 - Production/Stable
Classifier: Topic :: Scientific/Engineering
Classifier: Intended Audience :: Science/Research
Classifier: Operating System :: OS Independent
Classifier: Programming Language :: Python
Classifier: Programming Language :: Python :: 3
Classifier: Programming Language :: Python :: 3.8
Classifier: Programming Language :: Python :: 3.9
Classifier: Programming Language :: Python :: 3.10
Classifier: License :: OSI Approved :: MIT License
Requires-Python: >=3.8
License-File: LICENSE.txt
Requires-Dist: cf_pandas
Requires-Dist: intake
Requires-Dist: noaa_coops
Requires-Dist: numpy
Requires-Dist: pandas
Requires-Dist: xarray
Dynamic: license-file
